latticeModelMashup/GUI.py
latticeModelMashup/__init__.py
latticeModelMashup/engineOperator.py
latticeModelMashup/imageProcessing.py
latticeModelMashup/taskman.py
latticeModelMashup/updaters.py
LatticeModelMashup-0.98.3.dist-info/LICENSE
LatticeModelMashup-0.98.3.dist-info/METADATA
LatticeModelMashup-0.98.3.dist-info/WHEEL
LatticeModelMashup-0.98.3.dist-info/entry_points.txt
LatticeModelMashup-0.98.3.dist-info/top_level.txt
LatticeModelMashup-0.98.3.dist-info/RECORD
