Metadata-Version: 2.1
Name: LatticeModelMashup
Version: 0.98.3
Summary: An ungodly mixture of lattice models
Home-page: https://github.com/fergusfettes/lattice
Author: Fergus Fettes
Author-email: fergusfettes@gmail.com
License: UNKNOWN
Platform: UNKNOWN
Classifier: Programming Language :: Python :: 3.6
Classifier: Topic :: Games/Entertainment :: Simulation
Classifier: License :: OSI Approved :: GNU Lesser General Public License v3 (LGPLv3)
Classifier: Development Status :: 4 - Beta
Classifier: Operating System :: POSIX :: Linux
Requires-Dist: imageio
Requires-Dist: numpy
Requires-Dist: pyqt5
Requires-Dist: ffmpeg-python
